AUTHORS
CHANGELOG.md
LICENSE
MANIFEST.in
README.rst
VERSION.py
setup.cfg
setup.py
route4me/sdk/__init__.py
route4me/sdk/__main__.py
route4me/sdk/_net.py
route4me/sdk/enums.py
route4me/sdk/errors.py
route4me/sdk/version.py
route4me/sdk/_internals/__init__.py
route4me/sdk/_internals/utils.py
route4me/sdk/models/__init__.py
route4me/sdk/resources/__init__.py
route4me/sdk/resources/geocodings.py
route4me/sdk/resources/members.py
route4me/sdk/resources/optimizations.py
route4me/sdk/resources/telematics.py
route4me/sdk/utils/__init__.py
route4me/sdk/utils/typeconv.py
route4me_sdk.egg-info/PKG-INFO
route4me_sdk.egg-info/SOURCES.txt
route4me_sdk.egg-info/dependency_links.txt
route4me_sdk.egg-info/requires.txt
route4me_sdk.egg-info/top_level.txt
route4me_sdk.egg-info/zip-safe